vedro_interactive/__init__.py
vedro_interactive/_interactive_plugin.py
vedro_interactive/py.typed
vedro_interactive-0.0.3.dist-info/LICENSE
vedro_interactive-0.0.3.dist-info/METADATA
vedro_interactive-0.0.3.dist-info/WHEEL
vedro_interactive-0.0.3.dist-info/top_level.txt
vedro_interactive-0.0.3.dist-info/RECORD
