Metadata-Version: 2.1
Name: vedro-interactive
Version: 0.0.3
Home-page: https://github.com/nikitanovosibirsk/vedro-interactive
Author: Nikita Tsvetkov
Author-email: nikitanovosibirsk@yandex.com
License: Apache-2.0
Classifier: License :: OSI Approved :: Apache Software License
Classifier: Programming Language :: Python :: 3.8
Classifier: Programming Language :: Python :: 3.9
Classifier: Programming Language :: Python :: 3.10
Classifier: Typing :: Typed
Requires-Python: >=3.8
License-File: LICENSE
Requires-Dist: vedro (<2.0,>=1.5)
Requires-Dist: rich (<13.0,>=10.0)
